{"cameraMode":{"drawMode":0,"name":"Shaded","section":"Shading Mode"},"sceneLighting":false,"audioPlay":false,"sceneViewState":{"m_AlwaysRefresh":false,"showFog":true,"showSkybox":false,"showFlares":true,"showImageEffects":true,"showParticleSystems":true,"showVisualEffectGraphs":true,"m_FxEnabled":true},"in2DMode":false,"pivot":{"x":785.219482421875,"y":587.1351928710938,"z":0.0},"rotation":{"x":0.16456401348114015,"y":-0.22422470152378083,"z":0.03844810649752617,"w":0.9597793221473694},"size":0.9229947328567505,"orthographic":false}